shred/__init__.py
shred/cbase.py
shred/core.py
shred/libtoken.dll.a
shred/libtoken.pyd
shred/word.py
shredword-0.1.2.dist-info/METADATA
shredword-0.1.2.dist-info/WHEEL
shredword-0.1.2.dist-info/licenses/LICENSE
shredword-0.1.2.dist-info/RECORD
